audioflux/__init__.py
audioflux/__version__.py
audioflux/audio.py
audioflux/base.py
audioflux/bft.py
audioflux/cepstrogram.py
audioflux/core.py
audioflux/cqt.py
audioflux/cwt.py
audioflux/dwt.py
audioflux/fftlib.py
audioflux/fst.py
audioflux/nsgt.py
audioflux/pwt.py
audioflux/reassign.py
audioflux/spectrogram.py
audioflux/st.py
audioflux/stft.py
audioflux/swt.py
audioflux/synsq.py
audioflux/temporal.py
audioflux/wpt.py
audioflux/wsst.py
audioflux/classic/__init__.py
audioflux/classic/nmf.py
audioflux/display/__init__.py
audioflux/display/display.py
audioflux/display/plot.py
audioflux/dsp/__init__.py
audioflux/dsp/czt.py
audioflux/dsp/resample.py
audioflux/dsp/xcorr.py
audioflux/feature/__init__.py
audioflux/feature/deconv.py
audioflux/feature/extractor.py
audioflux/feature/spectral.py
audioflux/feature/xxcc.py
audioflux/lib/libaudioflux.dll
audioflux/lib/libaudioflux.dylib
audioflux/lib/libaudioflux.so
audioflux/lib/libfftw3f-3.dll
audioflux/lib/lib/libmkl_core.so.2
audioflux/lib/lib/libmkl_def.so.2
audioflux/lib/lib/libmkl_intel_lp64.so.2
audioflux/lib/lib/libmkl_intel_thread.so.2
audioflux/lib/lib/libomp.dylib
audioflux/lib/lib/libomp.so.5
audioflux/mir/__init__.py
audioflux/mir/harmonic.py
audioflux/mir/harmonic_ratio.py
audioflux/mir/hpss.py
audioflux/mir/onset.py
audioflux/mir/pitch_cep.py
audioflux/mir/pitch_ffp.py
audioflux/mir/pitch_hps.py
audioflux/mir/pitch_lhs.py
audioflux/mir/pitch_ncf.py
audioflux/mir/pitch_pef.py
audioflux/mir/pitch_shift.py
audioflux/mir/pitch_stft.py
audioflux/mir/pitch_yin.py
audioflux/mir/time_stretch.py
audioflux/type/__init__.py
audioflux/type/basic.py
audioflux/type/nsgt.py
audioflux/type/onset.py
audioflux/type/pitch.py
audioflux/type/reassign.py
audioflux/type/resample.py
audioflux/type/xcorr.py
audioflux/utils/__init__.py
audioflux/utils/auditory_weight.py
audioflux/utils/convert.py
audioflux/utils/queue.py
audioflux/utils/sample.py
audioflux/utils/scale.py
audioflux/utils/util.py
audioflux/utils/sample_data/220.wav
audioflux-0.1.9.dist-info/LICENSE.md
audioflux-0.1.9.dist-info/METADATA
audioflux-0.1.9.dist-info/WHEEL
audioflux-0.1.9.dist-info/top_level.txt
audioflux-0.1.9.dist-info/RECORD
