Metadata-Version: 2.1
Name: audioflux
Version: 0.1.9
Summary: A library for audio and music analysis, feature extraction.
Home-page: https://audioflux.top
Author: audioflux
License: MIT
Project-URL: Source, https://github.com/libAudioFlux/audioFlux
Keywords: audioflux
Classifier: License :: OSI Approved :: MIT License
Classifier: Development Status :: 3 - Alpha
Classifier: Intended Audience :: Science/Research
Classifier: Intended Audience :: Developers
Classifier: Framework :: Matplotlib
Classifier: Programming Language :: C
Classifier: Programming Language :: Python :: 3
Classifier: Programming Language :: Python :: 3.6
Classifier: Programming Language :: Python :: 3.7
Classifier: Programming Language :: Python :: 3.8
Classifier: Programming Language :: Python :: 3.9
Classifier: Programming Language :: Python :: 3.10
Classifier: Programming Language :: Python :: 3.11
Classifier: Programming Language :: Python :: 3.12
Requires-Python: >=3.6
License-File: LICENSE.md
Requires-Dist: numpy
Requires-Dist: scipy (>=1.2.0)
Requires-Dist: soundfile (>=0.12.1)
Requires-Dist: matplotlib
